{
  "DataBase":[
    {
      "CODIGO CLIENTE": 9206760,
      "TIPO DOC": "C",
      "NRO DOC": 9206760,
      "NOMBRE CLIENTE": "CAPCHA TORRES GLADIS DONATILA",
      "MONTO PRESTAMO": 2158.03,
      "CODIGO PRESTAMO": 330033428,
      "DIAS MORA": 2153,
      "MONEDA": "MNA",
      "CANT CLIEN": 8,
      "AGENCIA": "CANTO GRANDE",
      "ZONA": "S.J. LURIGANCHO",
      "TERRITORIAL": "STEVE CUEVA",
      "SUPERVISOR": "JOSE SILVERIO",
      "EJECUTIVO": "EDGAR CALLE",
      "TRAMO": "T F 721-MAS",
      "ESTADO": "C",
      "EDR ANTE": "Hugo Arias",
      "EDR ASIG": "EDGAR CALLE",
      "EDR SUPER": "EDGAR CALLE",
      "MONTO CUOTA": 127.36,
      "NRO CUOTA": 0,
      "FECH INIC": "01/01/2010",
      "FECH VENCI": "30/07/2013"
    },
    {
      "CODIGO CLIENTE": 9206760,
      "TIPO DOC": "C",
      "NRO DOC": 9206760,
      "NOMBRE CLIENTE": "CAPCHA TORRES GLADIS DONATILA",
      "MONTO PRESTAMO": 2624.69,
      "CODIGO PRESTAMO": 330038280,
      "DIAS MORA": 2158,
      "MONEDA": "MNA",
      "CANT CLIEN": 5,
      "AGENCIA": "CANTO GRANDE",
      "ZONA": "S.J. LURIGANCHO",
      "TERRITORIAL": "STEVE CUEVA",
      "SUPERVISOR": "JOSE SILVERIO",
      "EJECUTIVO": "EDGAR CALLE",
      "TRAMO": "T F 721-MAS",
      "ESTADO": "C",
      "EDR ANTE": "Hugo Arias",
      "EDR ASIG": "EDGAR CALLE",
      "EDR SUPER": "EDGAR CALLE",
      "MONTO CUOTA": 219.52,
      "NRO CUOTA": 0,
      "FECH INIC": "02/01/2010",
      "FECH VENCI": "31/07/2013"
    },
    {
      "CODIGO CLIENTE": 10105125,
      "TIPO DOC": "C",
      "NRO DOC": 10105125,
      "NOMBRE CLIENTE": "HUAJACHI LLACMA ROSA MARIA",
      "MONTO PRESTAMO": 3415.41,
      "CODIGO PRESTAMO": 100233239,
      "DIAS MORA": 7908,
      "MONEDA": "MNA",
      "CANT CLIEN": 51,
      "AGENCIA": "CANTO GRANDE",
      "ZONA": "S.J. LURIGANCHO",
      "TERRITORIAL": "STEVE CUEVA",
      "SUPERVISOR": "JOSE SILVERIO",
      "EJECUTIVO": "TRIFON CHAMBI",
      "TRAMO": "T F 721-MAS",
      "ESTADO": "C",
      "EDR ANTE": "Hugo Arias",
      "EDR ASIG": "TRIFON CHAMBI",
      "EDR SUPER": "TRIFON CHAMBI",
      "MONTO CUOTA": 716.18,
      "NRO CUOTA": 0,
      "FECH INIC": "03/01/2010",
      "FECH VENCI": "01/08/2013"
    },
    {
      "CODIGO CLIENTE": 10511053,
      "TIPO DOC": "C",
      "NRO DOC": 10511053,
      "NOMBRE CLIENTE": "ATALAYA CHACON CARLOS ELIAS",
      "MONTO PRESTAMO": 7215.5,
      "CODIGO PRESTAMO": 337806933,
      "DIAS MORA": 4748,
      "MONEDA": "MNA",
      "CANT CLIEN": 83,
      "AGENCIA": "PROCERES",
      "ZONA": "S.J. LURIGANCHO",
      "TERRITORIAL": "STEVE CUEVA",
      "SUPERVISOR": "JOSE SILVERIO",
      "EJECUTIVO": "WILFREDO BUIZA",
      "TRAMO": "T F 721-MAS",
      "ESTADO": "C",
      "EDR ANTE": "Hugo Arias",
      "EDR ASIG": "WILFREDO BUIZA",
      "EDR SUPER": "WILFREDO BUIZA",
      "MONTO CUOTA": 114.74,
      "NRO CUOTA": 0,
      "FECH INIC": "04/01/2010",
      "FECH VENCI": "02/08/2013"
    },
    {
      "CODIGO CLIENTE": 9658346,
      "TIPO DOC": "C",
      "NRO DOC": 9658346,
      "NOMBRE CLIENTE": "ALTAMIRANO GUEVARA MARIBEL CLEOTILDE",
      "MONTO PRESTAMO": 11836.46,
      "CODIGO PRESTAMO": 110904504,
      "DIAS MORA": 132,
      "MONEDA": "MNA",
      "CANT CLIEN": 614,
      "AGENCIA": "CANTO GRANDE",
      "ZONA": "S.J. LURIGANCHO",
      "TERRITORIAL": "STEVE CUEVA",
      "SUPERVISOR": "JOSE SILVERIO",
      "EJECUTIVO": "EDWAR HOLGADO",
      "TRAMO": "T E 121-720",
      "ESTADO": "A",
      "EDR ANTE": "Julio Moreno",
      "EDR ASIG": "EDWAR HOLGADO",
      "EDR SUPER": "EDWAR HOLGADO",
      "MONTO CUOTA": 10715.77,
      "NRO CUOTA": 9,
      "FECH INIC": "05/01/2010",
      "FECH VENCI": "03/08/2013"
    },
    {
      "CODIGO CLIENTE": 9658346,
      "TIPO DOC": "C",
      "NRO DOC": 9658346,
      "NOMBRE CLIENTE": "ALTAMIRANO GUEVARA MARIBEL CLEOTILDE",
      "MONTO PRESTAMO": 20769.13,
      "CODIGO PRESTAMO": 111469011,
      "DIAS MORA": 140,
      "MONEDA": "MNA",
      "CANT CLIEN": 1406,
      "AGENCIA": "CANTO GRANDE",
      "ZONA": "S.J. LURIGANCHO",
      "TERRITORIAL": "STEVE CUEVA",
      "SUPERVISOR": "JOSE SILVERIO",
      "EJECUTIVO": "EDWAR HOLGADO",
      "TRAMO": "T E 121-720",
      "ESTADO": "A",
      "EDR ANTE": "Yarnold",
      "EDR ASIG": "EDWAR HOLGADO",
      "EDR SUPER": "EDWAR HOLGADO",
      "MONTO CUOTA": 4253,
      "NRO CUOTA": 6,
      "FECH INIC": "06/01/2010",
      "FECH VENCI": "04/08/2013"
    },
    {
      "CODIGO CLIENTE": 9658346,
      "TIPO DOC": "C",
      "NRO DOC": 9658346,
      "NOMBRE CLIENTE": "ALTAMIRANO GUEVARA MARIBEL CLEOTILDE",
      "MONTO PRESTAMO": 5880.31,
      "CODIGO PRESTAMO": 112262938,
      "DIAS MORA": 121,
      "MONEDA": "MNA",
      "CANT CLIEN": 3,
      "AGENCIA": "CANTO GRANDE",
      "ZONA": "S.J. LURIGANCHO",
      "TERRITORIAL": "STEVE CUEVA",
      "SUPERVISOR": "JOSE SILVERIO",
      "EJECUTIVO": "EDWAR HOLGADO",
      "TRAMO": "T E 121-720",
      "ESTADO": "A",
      "EDR ANTE": "PERCY MEJIA",
      "EDR ASIG": "EDWAR HOLGADO",
      "EDR SUPER": "EDWAR HOLGADO",
      "MONTO CUOTA": 261.16,
      "NRO CUOTA": 3,
      "FECH INIC": "07/01/2010",
      "FECH VENCI": "05/08/2013"
    },
    {
      "CODIGO CLIENTE": 9093678,
      "TIPO DOC": "C",
      "NRO DOC": 9093678,
      "NOMBRE CLIENTE": "PACHECO MENDOZA LUZ MARIA",
      "MONTO PRESTAMO": 1488.84,
      "CODIGO PRESTAMO": 330012074,
      "DIAS MORA": 3550,
      "MONEDA": "MNA",
      "CANT CLIEN": 9,
      "AGENCIA": "RIMAC MATRIZ",
      "ZONA": "AGUSTINO - RIMAC",
      "TERRITORIAL": "LUIS CHUQUICHAICO",
      "SUPERVISOR": "CARLOS CONDORE",
      "EJECUTIVO": "SANDRO CRUZ",
      "TRAMO": "T F 721-MAS",
      "ESTADO": "C",
      "EDR ANTE": "PERCY MEJIA",
      "EDR ASIG": "SANDRO CRUZ",
      "EDR SUPER": "SANDRO CRUZ",
      "MONTO CUOTA": 122.36,
      "NRO CUOTA": 0,
      "FECH INIC": "08/01/2010",
      "FECH VENCI": "06/08/2013"
    },
    {
      "CODIGO CLIENTE": 6770936,
      "TIPO DOC": "C",
      "NRO DOC": 6770936,
      "NOMBRE CLIENTE": "VILLARROEL VASQUEZ GLADYS SOLEDAD",
      "MONTO PRESTAMO": 1441.63,
      "CODIGO PRESTAMO": 330006199,
      "DIAS MORA": 3951,
      "MONEDA": "MNA",
      "CANT CLIEN": 63,
      "AGENCIA": "TANTAMAYO",
      "ZONA": "LOS OLIVOS",
      "TERRITORIAL": "MAX MORALES [E]",
      "SUPERVISOR": "ROQUE ORELLANA",
      "EJECUTIVO": "MIGUEL MENDOZA",
      "TRAMO": "T F 721-MAS",
      "ESTADO": "C",
      "EDR ANTE": "PERCY MEJIA",
      "EDR ASIG": "MIGUEL MENDOZA",
      "EDR SUPER": "MIGUEL MENDOZA",
      "MONTO CUOTA": 110.11,
      "NRO CUOTA": 0,
      "FECH INIC": "09/01/2010",
      "FECH VENCI": "07/08/2013"
    },
    {
      "CODIGO CLIENTE": 6196079,
      "TIPO DOC": "C",
      "NRO DOC": 6196079,
      "NOMBRE CLIENTE": "CAMPOS VINCES MILTON",
      "MONTO PRESTAMO": 1632.82,
      "CODIGO PRESTAMO": 330032413,
      "DIAS MORA": 2401,
      "MONEDA": "MNA",
      "CANT CLIEN": 81,
      "AGENCIA": "ZARATE",
      "ZONA": "S.J. LURIGANCHO",
      "TERRITORIAL": "STEVE CUEVA",
      "SUPERVISOR": "JOSE SILVERIO",
      "EJECUTIVO": "BENJAMIN SILVA",
      "TRAMO": "T F 721-MAS",
      "ESTADO": "C",
      "EDR ANTE": "PERCY MEJIA",
      "EDR ASIG": "BENJAMIN SILVA",
      "EDR SUPER": "BENJAMIN SILVA",
      "MONTO CUOTA": 226.59,
      "NRO CUOTA": 0,
      "FECH INIC": "10/01/2010",
      "FECH VENCI": "08/08/2013"
    },
    {
      "CODIGO CLIENTE": 9199872,
      "TIPO DOC": "C",
      "NRO DOC": 9199872,
      "NOMBRE CLIENTE": "CHIRE FLORES JUAN GUALBERTO",
      "MONTO PRESTAMO": 34721.66,
      "CODIGO PRESTAMO": 111809312,
      "DIAS MORA": 150,
      "MONEDA": "MNA",
      "CANT CLIEN": 467,
      "AGENCIA": "ZARATE",
      "ZONA": "S.J. LURIGANCHO",
      "TERRITORIAL": "STEVE CUEVA",
      "SUPERVISOR": "JOSE SILVERIO",
      "EJECUTIVO": "ALEX RUIZ",
      "TRAMO": "T E 121-720",
      "ESTADO": "A",
      "EDR ANTE": "PERCY MEJIA",
      "EDR ASIG": "ALEX RUIZ",
      "EDR SUPER": "ALEX RUIZ",
      "MONTO CUOTA": 3656.09,
      "NRO CUOTA": 4,
      "FECH INIC": "11/01/2010",
      "FECH VENCI": "09/08/2013"
    },
    {
      "CODIGO CLIENTE": 8112729,
      "TIPO DOC": "C",
      "NRO DOC": 8112729,
      "NOMBRE CLIENTE": "TORRES IPINCE GUILLERMO",
      "MONTO PRESTAMO": 11367.73,
      "CODIGO PRESTAMO": 109437940,
      "DIAS MORA": 234,
      "MONEDA": "MNA",
      "CANT CLIEN": 1292,
      "AGENCIA": "RIMAC ALCAZAR",
      "ZONA": "AGUSTINO - RIMAC",
      "TERRITORIAL": "LUIS CHUQUICHAICO",
      "SUPERVISOR": "CARLOS CONDORE",
      "EJECUTIVO": "JAVIER SCARGGLIONI",
      "TRAMO": "T E 121-720",
      "ESTADO": "A",
      "EDR ANTE": "Kobranzas",
      "EDR ASIG": "JAVIER SCARGGLIONI",
      "EDR SUPER": "JAVIER SCARGGLIONI",
      "MONTO CUOTA": 2077.13,
      "NRO CUOTA": 13,
      "FECH INIC": "12/01/2010",
      "FECH VENCI": "10/08/2013"
    },
    {
      "CODIGO CLIENTE": 9126323,
      "TIPO DOC": "C",
      "NRO DOC": 9126323,
      "NOMBRE CLIENTE": "MARTINEZ JAJAYCUCHO ROSA MARIA",
      "MONTO PRESTAMO": 5633.25,
      "CODIGO PRESTAMO": 109457746,
      "DIAS MORA": 43,
      "MONEDA": "MNA",
      "CANT CLIEN": 1,
      "AGENCIA": "MARISCAL CACERES",
      "ZONA": "MARISCAL CACERES",
      "TERRITORIAL": "STEVE CUEVA",
      "SUPERVISOR": "JOSE SILVERIO",
      "EJECUTIVO": "ALAN MOGOLLON",
      "TRAMO": "T C 031-060",
      "ESTADO": "A",
      "EDR ANTE": "Henry Aceituno",
      "EDR ASIG": "ALAN MOGOLLON",
      "EDR SUPER": "ALAN MOGOLLON",
      "MONTO CUOTA": 6434.69,
      "NRO CUOTA": 19,
      "FECH INIC": "13/01/2010",
      "FECH VENCI": "11/08/2013"
    },
    {
      "CODIGO CLIENTE": 10518824,
      "TIPO DOC": "C",
      "NRO DOC": 10518824,
      "NOMBRE CLIENTE": "SANCHEZ GUTIERREZ MANUEL RICARDO",
      "MONTO PRESTAMO": 1292.84,
      "CODIGO PRESTAMO": 330012222,
      "DIAS MORA": 3498,
      "MONEDA": "MNA",
      "CANT CLIEN": 3,
      "AGENCIA": "MARISCAL CACERES",
      "ZONA": "MARISCAL CACERES",
      "TERRITORIAL": "STEVE CUEVA",
      "SUPERVISOR": "JOSE SILVERIO",
      "EJECUTIVO": "GUSTAVO RIVERA",
      "TRAMO": "T F 721-MAS",
      "ESTADO": "C",
      "EDR ANTE": "Henry Aceituno",
      "EDR ASIG": "GUSTAVO RIVERA",
      "EDR SUPER": "GUSTAVO RIVERA",
      "MONTO CUOTA": 115.68,
      "NRO CUOTA": 0,
      "FECH INIC": "14/01/2010",
      "FECH VENCI": "12/08/2013"
    },
    {
      "CODIGO CLIENTE": 10363762,
      "TIPO DOC": "C",
      "NRO DOC": 10363762,
      "NOMBRE CLIENTE": "FLORES GALVEZ ISABEL MARINA",
      "MONTO PRESTAMO": 3913.93,
      "CODIGO PRESTAMO": 110560578,
      "DIAS MORA": 34,
      "MONEDA": "MNA",
      "CANT CLIEN": 59,
      "AGENCIA": "BAYOVAR",
      "ZONA": "MARISCAL CACERES",
      "TERRITORIAL": "STEVE CUEVA",
      "SUPERVISOR": "JOSE SILVERIO",
      "EJECUTIVO": "JOEL PIMENTEL",
      "TRAMO": "T C 031-060",
      "ESTADO": "A",
      "EDR ANTE": "Henry Aceituno",
      "EDR ASIG": "JOEL PIMENTEL",
      "EDR SUPER": "JOEL PIMENTEL",
      "MONTO CUOTA": 7128.37,
      "NRO CUOTA": 14,
      "FECH INIC": "15/01/2010",
      "FECH VENCI": "13/08/2013"
    },
    {
      "CODIGO CLIENTE": 9198327,
      "TIPO DOC": "C",
      "NRO DOC": 9198327,
      "NOMBRE CLIENTE": "QUISPE PEREZ TORIBIO",
      "MONTO PRESTAMO": 1415.5,
      "CODIGO PRESTAMO": 105871586,
      "DIAS MORA": 1088,
      "MONEDA": "MNA",
      "CANT CLIEN": 77,
      "AGENCIA": "MARISCAL CACERES",
      "ZONA": "MARISCAL CACERES",
      "TERRITORIAL": "STEVE CUEVA",
      "SUPERVISOR": "JOSE SILVERIO",
      "EJECUTIVO": "ALEX BARDALEZ",
      "TRAMO": "T F 721-MAS",
      "ESTADO": "C",
      "EDR ANTE": "Henry Aceituno",
      "EDR ASIG": "ALEX BARDALEZ",
      "EDR SUPER": "ALEX BARDALEZ",
      "MONTO CUOTA": 53.79,
      "NRO CUOTA": 9,
      "FECH INIC": "16/01/2010",
      "FECH VENCI": "14/08/2013"
    },
    {
      "CODIGO CLIENTE": 6003964,
      "TIPO DOC": "C",
      "NRO DOC": 6003964,
      "NOMBRE CLIENTE": "GARCIA VILLANUEVA FILEMON",
      "MONTO PRESTAMO": 2207.6,
      "CODIGO PRESTAMO": 108618141,
      "DIAS MORA": 462,
      "MONEDA": "MNA",
      "CANT CLIEN": 479,
      "AGENCIA": "HUARAZ PLAZA",
      "ZONA": "HUARAZ",
      "TERRITORIAL": "STEVE CUEVA",
      "SUPERVISOR": "ALEJANDRO AVALOS",
      "EJECUTIVO": "HUGO ARIAS",
      "TRAMO": "T E 121-720",
      "ESTADO": "C",
      "EDR ANTE": "REYNALDO MAMANI",
      "EDR ASIG": "HUGO ARIAS",
      "EDR SUPER": "HUGO ARIAS",
      "MONTO CUOTA": 143.87,
      "NRO CUOTA": 11,
      "FECH INIC": "17/01/2010",
      "FECH VENCI": "15/08/2013"
    },
    {
      "CODIGO CLIENTE": 6003964,
      "TIPO DOC": "C",
      "NRO DOC": 6003964,
      "NOMBRE CLIENTE": "GARCIA VILLANUEVA FILEMON",
      "MONTO PRESTAMO": 7134.83,
      "CODIGO PRESTAMO": 110264406,
      "DIAS MORA": 472,
      "MONEDA": "MNA",
      "CANT CLIEN": 1138,
      "AGENCIA": "HUARAZ PLAZA",
      "ZONA": "HUARAZ",
      "TERRITORIAL": "STEVE CUEVA",
      "SUPERVISOR": "ALEJANDRO AVALOS",
      "EJECUTIVO": "HUGO ARIAS",
      "TRAMO": "T E 121-720",
      "ESTADO": "C",
      "EDR ANTE": "Inversiones",
      "EDR ASIG": "HUGO ARIAS",
      "EDR SUPER": "HUGO ARIAS",
      "MONTO CUOTA": 1153.29,
      "NRO CUOTA": 1,
      "FECH INIC": "18/01/2010",
      "FECH VENCI": "16/08/2013"
    },
    {
      "CODIGO CLIENTE": 10536994,
      "TIPO DOC": "C",
      "NRO DOC": 10536994,
      "NOMBRE CLIENTE": "ZAVALETA AGUILAR LUCILA ANITA",
      "MONTO PRESTAMO": 11798.4,
      "CODIGO PRESTAMO": 108999759,
      "DIAS MORA": 293,
      "MONEDA": "MNA",
      "CANT CLIEN": 7,
      "AGENCIA": "COVIDA",
      "ZONA": "LOS OLIVOS",
      "TERRITORIAL": "MAX MORALES [E]",
      "SUPERVISOR": "DIANA PLAZA",
      "EJECUTIVO": "PELAGIO AMESQUITA",
      "TRAMO": "T E 121-720",
      "ESTADO": "A",
      "EDR ANTE": "Edgar Calle",
      "EDR ASIG": "PELAGIO AMESQUITA",
      "EDR SUPER": "PELAGIO AMESQUITA",
      "MONTO CUOTA": 3039.36,
      "NRO CUOTA": 14,
      "FECH INIC": "19/01/2010",
      "FECH VENCI": "17/08/2013"
    },
    {
      "CODIGO CLIENTE": 8924783,
      "TIPO DOC": "C",
      "NRO DOC": 8924783,
      "NOMBRE CLIENTE": "LARA DIAZ DE AYALA ADELFA",
      "MONTO PRESTAMO": 42660.08,
      "CODIGO PRESTAMO": 106132375,
      "DIAS MORA": 1179,
      "MONEDA": "MNA",
      "CANT CLIEN": 7,
      "AGENCIA": "SAN JUAN DE MIRAFLORES MATRIZ",
      "ZONA": "S.J. MIRAFLORES",
      "TERRITORIAL": "STEVE CUEVA",
      "SUPERVISOR": "HUGO URIARTE",
      "EJECUTIVO": "MANUEL SUCLUPE",
      "TRAMO": "T F 721-MAS",
      "ESTADO": "C",
      "EDR ANTE": "Edgar Calle",
      "EDR ASIG": "MANUEL SUCLUPE",
      "EDR SUPER": "MANUEL SUCLUPE",
      "MONTO CUOTA": 5846.58,
      "NRO CUOTA": 4,
      "FECH INIC": "20/01/2010",
      "FECH VENCI": "18/08/2013"
    },
    {
      "CODIGO CLIENTE": 8276944,
      "TIPO DOC": "C",
      "NRO DOC": 8276944,
      "NOMBRE CLIENTE": "TORRES LIZARBE JUAN RODOLFO",
      "MONTO PRESTAMO": 1435.29,
      "CODIGO PRESTAMO": 104380320,
      "DIAS MORA": 1714,
      "MONEDA": "MNA",
      "CANT CLIEN": 53,
      "AGENCIA": "CANTO REY",
      "ZONA": "MARISCAL CACERES",
      "TERRITORIAL": "STEVE CUEVA",
      "SUPERVISOR": "JOSE SILVERIO",
      "EJECUTIVO": "ALAN PEREZ",
      "TRAMO": "T F 721-MAS",
      "ESTADO": "C",
      "EDR ANTE": "Manuel Acero",
      "EDR ASIG": "ALAN PEREZ",
      "EDR SUPER": "ALAN PEREZ",
      "MONTO CUOTA": 88.91,
      "NRO CUOTA": 2,
      "FECH INIC": "21/01/2010",
      "FECH VENCI": "19/08/2013"
    },
    {
      "CODIGO CLIENTE": 9207019,
      "TIPO DOC": "C",
      "NRO DOC": 9207019,
      "NOMBRE CLIENTE": "ABURTO ALCANTARA LILY HAIDEE",
      "MONTO PRESTAMO": 771.36,
      "CODIGO PRESTAMO": 113005928,
      "DIAS MORA": 1459,
      "MONEDA": "MNA",
      "CANT CLIEN": 57,
      "AGENCIA": "MARISCAL CACERES",
      "ZONA": "MARISCAL CACERES",
      "TERRITORIAL": "STEVE CUEVA",
      "SUPERVISOR": "JOSE SILVERIO",
      "EJECUTIVO": "JOSE FERNANDEZ",
      "TRAMO": "T F 721-MAS",
      "ESTADO": "C",
      "EDR ANTE": "Edgar Calle",
      "EDR ASIG": "JOSE FERNANDEZ",
      "EDR SUPER": "JOSE FERNANDEZ",
      "MONTO CUOTA": 39.3,
      "NRO CUOTA": 8,
      "FECH INIC": "22/01/2010",
      "FECH VENCI": "20/08/2013"
    },
    {
      "CODIGO CLIENTE": 9212140,
      "TIPO DOC": "C",
      "NRO DOC": 9212140,
      "NOMBRE CLIENTE": "BLAS GOMERO GLADYS CONSTANZA",
      "MONTO PRESTAMO": 809,
      "CODIGO PRESTAMO": 100302448,
      "DIAS MORA": 7896,
      "MONEDA": "MNA",
      "CANT CLIEN": 519,
      "AGENCIA": "SAN JUAN DE LURIGANCHO",
      "ZONA": "S.J. LURIGANCHO",
      "TERRITORIAL": "STEVE CUEVA",
      "SUPERVISOR": "JOSE SILVERIO",
      "EJECUTIVO": "JUAN BACA",
      "TRAMO": "T F 721-MAS",
      "ESTADO": "C",
      "EDR ANTE": "William Peña",
      "EDR ASIG": "JUAN BACA",
      "EDR SUPER": "JUAN BACA",
      "MONTO CUOTA": 134.07,
      "NRO CUOTA": 0,
      "FECH INIC": "23/01/2010",
      "FECH VENCI": "21/08/2013"
    },
    {
      "CODIGO CLIENTE": 8343580,
      "TIPO DOC": "C",
      "NRO DOC": 8343580,
      "NOMBRE CLIENTE": "CUBA VALENZUELA MARIA GUILLERMINA",
      "MONTO PRESTAMO": 3006.44,
      "CODIGO PRESTAMO": 135293820,
      "DIAS MORA": 7893,
      "MONEDA": "MNA",
      "CANT CLIEN": 1056,
      "AGENCIA": "SAN JUAN DE LURIGANCHO",
      "ZONA": "S.J. LURIGANCHO",
      "TERRITORIAL": "STEVE CUEVA",
      "SUPERVISOR": "JOSE SILVERIO",
      "EJECUTIVO": "LIVER CAMPOS",
      "TRAMO": "T F 721-MAS",
      "ESTADO": "C",
      "EDR ANTE": "Yarnold",
      "EDR ASIG": "LIVER CAMPOS",
      "EDR SUPER": "LIVER CAMPOS",
      "MONTO CUOTA": 804.93,
      "NRO CUOTA": 0,
      "FECH INIC": "24/01/2010",
      "FECH VENCI": "22/08/2013"
    },
    {
      "CODIGO CLIENTE": 9235977,
      "TIPO DOC": "C",
      "NRO DOC": 9235977,
      "NOMBRE CLIENTE": "BALLARTA SUAZO DE MICHUY TEODOSIA VICTORIA",
      "MONTO PRESTAMO": 542.89,
      "CODIGO PRESTAMO": 103939374,
      "DIAS MORA": 7887,
      "MONEDA": "USD",
      "CANT CLIEN": 5,
      "AGENCIA": "SAN JUAN DE LURIGANCHO",
      "ZONA": "S.J. LURIGANCHO",
      "TERRITORIAL": "STEVE CUEVA",
      "SUPERVISOR": "JOSE SILVERIO",
      "EJECUTIVO": "AMADO RENGIFO",
      "TRAMO": "T F 721-MAS",
      "ESTADO": "C",
      "EDR ANTE": "LENIN SOTELO",
      "EDR ASIG": "AMADO RENGIFO",
      "EDR SUPER": "AMADO RENGIFO",
      "MONTO CUOTA": 0,
      "NRO CUOTA": 0,
      "FECH INIC": "25/01/2010",
      "FECH VENCI": "23/08/2013"
    },
    {
      "CODIGO CLIENTE": 6960294,
      "TIPO DOC": "C",
      "NRO DOC": 6960294,
      "NOMBRE CLIENTE": "RABINEZ VERA SUSANA MARIA",
      "MONTO PRESTAMO": 780.05,
      "CODIGO PRESTAMO": 100774751,
      "DIAS MORA": 3921,
      "MONEDA": "MNA",
      "CANT CLIEN": 2,
      "AGENCIA": "CANTO GRANDE",
      "ZONA": "S.J. LURIGANCHO",
      "TERRITORIAL": "STEVE CUEVA",
      "SUPERVISOR": "JOSE SILVERIO",
      "EJECUTIVO": "EDI VASQUEZ",
      "TRAMO": "T F 721-MAS",
      "ESTADO": "C",
      "EDR ANTE": "LENIN SOTELO",
      "EDR ASIG": "EDI VASQUEZ",
      "EDR SUPER": "EDI VASQUEZ",
      "MONTO CUOTA": 53.2,
      "NRO CUOTA": 2,
      "FECH INIC": "26/01/2010",
      "FECH VENCI": "24/08/2013"
    },
    {
      "CODIGO CLIENTE": 7399157,
      "TIPO DOC": "C",
      "NRO DOC": 7399157,
      "NOMBRE CLIENTE": "BERNABE GUTIERRES GENARO",
      "MONTO PRESTAMO": 532.71,
      "CODIGO PRESTAMO": 149429281,
      "DIAS MORA": 7880,
      "MONEDA": "MNA",
      "CANT CLIEN": 46,
      "AGENCIA": "SAN JUAN DE LURIGANCHO",
      "ZONA": "S.J. LURIGANCHO",
      "TERRITORIAL": "STEVE CUEVA",
      "SUPERVISOR": "JOSE SILVERIO",
      "EJECUTIVO": "CHRISTIAN REYES",
      "TRAMO": "T F 721-MAS",
      "ESTADO": "C",
      "EDR ANTE": "LENIN SOTELO",
      "EDR ASIG": "CHRISTIAN REYES",
      "EDR SUPER": "CHRISTIAN REYES",
      "MONTO CUOTA": 41.28,
      "NRO CUOTA": 0,
      "FECH INIC": "27/01/2010",
      "FECH VENCI": "25/08/2013"
    },
    {
      "CODIGO CLIENTE": 9725619,
      "TIPO DOC": "C",
      "NRO DOC": 9725619,
      "NOMBRE CLIENTE": "SALAS MEDINA MIGUEL ANTONIO",
      "MONTO PRESTAMO": 15097.57,
      "CODIGO PRESTAMO": 149453591,
      "DIAS MORA": 1590,
      "MONEDA": "MNA",
      "CANT CLIEN": 52,
      "AGENCIA": "SAN JUAN DE MIRAFLORES MATRIZ",
      "ZONA": "S.J. MIRAFLORES",
      "TERRITORIAL": "STEVE CUEVA",
      "SUPERVISOR": "HUGO URIARTE",
      "EJECUTIVO": "EDISON TEMOCHE",
      "TRAMO": "T F 721-MAS",
      "ESTADO": "C",
      "EDR ANTE": "LENIN SOTELO",
      "EDR ASIG": "EDISON TEMOCHE",
      "EDR SUPER": "EDISON TEMOCHE",
      "MONTO CUOTA": 0,
      "NRO CUOTA": 13,
      "FECH INIC": "28/01/2010",
      "FECH VENCI": "26/08/2013"
    },
    {
      "CODIGO CLIENTE": 9122806,
      "TIPO DOC": "C",
      "NRO DOC": 9122806,
      "NOMBRE CLIENTE": "MOSCAIZA GAMONAL GLADIS SEGUNDINA",
      "MONTO PRESTAMO": 1253.67,
      "CODIGO PRESTAMO": 100563343,
      "DIAS MORA": 7466,
      "MONEDA": "MNA",
      "CANT CLIEN": 381,
      "AGENCIA": "SAN JUAN DE MIRAFLORES",
      "ZONA": "VILLA EL SALVADOR",
      "TERRITORIAL": "STEVE CUEVA",
      "SUPERVISOR": "HUGO URIARTE",
      "EJECUTIVO": "CESAR WU",
      "TRAMO": "T F 721-MAS",
      "ESTADO": "C",
      "EDR ANTE": "Fidel Valiente",
      "EDR ASIG": "CESAR WU",
      "EDR SUPER": "CESAR WU",
      "MONTO CUOTA": 0,
      "NRO CUOTA": 0,
      "FECH INIC": "29/01/2010",
      "FECH VENCI": "27/08/2013"
    },
    {
      "CODIGO CLIENTE": 7983488,
      "TIPO DOC": "C",
      "NRO DOC": 7983488,
      "NOMBRE CLIENTE": "AIBAR ESCOBAR DE SOTO NELI PAULINA",
      "MONTO PRESTAMO": 2222.38,
      "CODIGO PRESTAMO": 146780591,
      "DIAS MORA": 7860,
      "MONEDA": "MNA",
      "CANT CLIEN": 1287,
      "AGENCIA": "PUENTE PIEDRA MATRIZ",
      "ZONA": "PUENTE PIEDRA",
      "TERRITORIAL": "LUIS CHUQUICHAICO",
      "SUPERVISOR": "ALBERTO QUINTOS [E]",
      "EJECUTIVO": "PERCY PEREZ",
      "TRAMO": "T F 721-MAS",
      "ESTADO": "C",
      "EDR ANTE": "Kobranzas",
      "EDR ASIG": "PERCY PEREZ",
      "EDR SUPER": "PERCY PEREZ",
      "MONTO CUOTA": 437.84,
      "NRO CUOTA": 0,
      "FECH INIC": "30/01/2010",
      "FECH VENCI": "28/08/2013"
    },
    {
      "CODIGO CLIENTE": 8083510,
      "TIPO DOC": "C",
      "NRO DOC": 8083510,
      "NOMBRE CLIENTE": "YRAITA OSCO CARLOS AMADO",
      "MONTO PRESTAMO": 440.32,
      "CODIGO PRESTAMO": 100139664,
      "DIAS MORA": 7090,
      "MONEDA": "USD",
      "CANT CLIEN": 3,
      "AGENCIA": "SAN JUAN DE LURIGANCHO",
      "ZONA": "S.J. LURIGANCHO",
      "TERRITORIAL": "STEVE CUEVA",
      "SUPERVISOR": "JOSE SILVERIO",
      "EJECUTIVO": "JULIA LA TORRE",
      "TRAMO": "T F 721-MAS",
      "ESTADO": "C",
      "EDR ANTE": "Yony Tello",
      "EDR ASIG": "JULIA LA TORRE",
      "EDR SUPER": "JULIA LA TORRE",
      "MONTO CUOTA": 0,
      "NRO CUOTA": 0,
      "FECH INIC": "31/01/2010",
      "FECH VENCI": "29/08/2013"
    },
    {
      "CODIGO CLIENTE": 9097458,
      "TIPO DOC": "C",
      "NRO DOC": 9097458,
      "NOMBRE CLIENTE": "SAIRITUPAC TORRES ONORATA BERARDA",
      "MONTO PRESTAMO": 26830.22,
      "CODIGO PRESTAMO": 112328524,
      "DIAS MORA": 899,
      "MONEDA": "MNA",
      "CANT CLIEN": 7,
      "AGENCIA": "MARISCAL CACERES",
      "ZONA": "MARISCAL CACERES",
      "TERRITORIAL": "STEVE CUEVA",
      "SUPERVISOR": "JOSE SILVERIO",
      "EJECUTIVO": "NARCISO CUBA",
      "TRAMO": "T F 721-MAS",
      "ESTADO": "C",
      "EDR ANTE": "Yony Tello",
      "EDR ASIG": "NARCISO CUBA",
      "EDR SUPER": "NARCISO CUBA",
      "MONTO CUOTA": 0,
      "NRO CUOTA": 46,
      "FECH INIC": "01/02/2010",
      "FECH VENCI": "30/08/2013"
    },
    {
      "CODIGO CLIENTE": 10098024,
      "TIPO DOC": "C",
      "NRO DOC": 10098024,
      "NOMBRE CLIENTE": "HUAMAN DE MACHADO HAYDEE MARGOT",
      "MONTO PRESTAMO": 15319.18,
      "CODIGO PRESTAMO": 107863522,
      "DIAS MORA": 358,
      "MONEDA": "MNA",
      "CANT CLIEN": 50,
      "AGENCIA": "TABLADA DE LURIN",
      "ZONA": "VILLA MARIA",
      "TERRITORIAL": "STEVE CUEVA",
      "SUPERVISOR": "JUAN LAZO",
      "EJECUTIVO": "CARLOS BOLIVAR",
      "TRAMO": "T E 121-720",
      "ESTADO": "A",
      "EDR ANTE": "Yony Tello",
      "EDR ASIG": "CARLOS BOLIVAR",
      "EDR SUPER": "CARLOS BOLIVAR",
      "MONTO CUOTA": 1899.7,
      "NRO CUOTA": 18,
      "FECH INIC": "02/02/2010",
      "FECH VENCI": "31/08/2013"
    },
    {
      "CODIGO CLIENTE": 8561279,
      "TIPO DOC": "C",
      "NRO DOC": 8561279,
      "NOMBRE CLIENTE": "QUISPE GAMBOA BERNABE PRUDENCIO",
      "MONTO PRESTAMO": 5933.45,
      "CODIGO PRESTAMO": 110254311,
      "DIAS MORA": 437,
      "MONEDA": "MNA",
      "CANT CLIEN": 80,
      "AGENCIA": "ZARATE",
      "ZONA": "S.J. LURIGANCHO",
      "TERRITORIAL": "STEVE CUEVA",
      "SUPERVISOR": "JOSE SILVERIO",
      "EJECUTIVO": "ADOLFO LUNA",
      "TRAMO": "T E 121-720",
      "ESTADO": "C",
      "EDR ANTE": "Yony Tello",
      "EDR ASIG": "ADOLFO LUNA",
      "EDR SUPER": "ADOLFO LUNA",
      "MONTO CUOTA": 1020.18,
      "NRO CUOTA": 2,
      "FECH INIC": "03/02/2010",
      "FECH VENCI": "01/09/2013"
    },
    {
      "CODIGO CLIENTE": 8555168,
      "TIPO DOC": "C",
      "NRO DOC": 8555168,
      "NOMBRE CLIENTE": "HIJUMA HAUXWELL DE GUTIERREZ MARCIA ESTHER",
      "MONTO PRESTAMO": 1718.93,
      "CODIGO PRESTAMO": 102245213,
      "DIAS MORA": 7861,
      "MONEDA": "MNA",
      "CANT CLIEN": 540,
      "AGENCIA": "LOS OLIVOS MATRIZ",
      "ZONA": "LOS OLIVOS",
      "TERRITORIAL": "MAX MORALES [E]",
      "SUPERVISOR": "ROQUE ORELLANA",
      "EJECUTIVO": "ANGEL SANDOVAL",
      "TRAMO": "T F 721-MAS",
      "ESTADO": "C",
      "EDR ANTE": "Javier Cisneros",
      "EDR ASIG": "ANGEL SANDOVAL",
      "EDR SUPER": "ANGEL SANDOVAL",
      "MONTO CUOTA": 697.06,
      "NRO CUOTA": 0,
      "FECH INIC": "04/02/2010",
      "FECH VENCI": "02/09/2013"
    },
    {
      "CODIGO CLIENTE": 8940682,
      "TIPO DOC": "C",
      "NRO DOC": 8940682,
      "NOMBRE CLIENTE": "MORALES CASTRO VICTORIA MARTHA",
      "MONTO PRESTAMO": 2767.41,
      "CODIGO PRESTAMO": 101769463,
      "DIAS MORA": 2702,
      "MONEDA": "MNA",
      "CANT CLIEN": 1549,
      "AGENCIA": "PACHACAMAC I ETAPA",
      "ZONA": "JOSE GALVEZ",
      "TERRITORIAL": "STEVE CUEVA",
      "SUPERVISOR": "OCTAVIO ALMONTE",
      "EJECUTIVO": "JORGE AQUINO",
      "TRAMO": "T F 721-MAS",
      "ESTADO": "C",
      "EDR ANTE": "Vertice",
      "EDR ASIG": "JORGE AQUINO",
      "EDR SUPER": "JORGE AQUINO",
      "MONTO CUOTA": 10,
      "NRO CUOTA": 10,
      "FECH INIC": "05/02/2010",
      "FECH VENCI": "03/09/2013"
    },
    {
      "CODIGO CLIENTE": 9147819,
      "TIPO DOC": "C",
      "NRO DOC": 9147819,
      "NOMBRE CLIENTE": "CACERES NAVARRO BENEDICTA CLAUDIA",
      "MONTO PRESTAMO": 1772.18,
      "CODIGO PRESTAMO": 100283150,
      "DIAS MORA": 6689,
      "MONEDA": "MNA",
      "CANT CLIEN": 3,
      "AGENCIA": "SAN JUAN DE MIRAFLORES",
      "ZONA": "VILLA EL SALVADOR",
      "TERRITORIAL": "STEVE CUEVA",
      "SUPERVISOR": "HUGO URIARTE",
      "EJECUTIVO": "CESAR GUZMAN",
      "TRAMO": "T F 721-MAS",
      "ESTADO": "C",
      "EDR ANTE": "Harold Chavez",
      "EDR ASIG": "CESAR GUZMAN",
      "EDR SUPER": "CESAR GUZMAN",
      "MONTO CUOTA": 301.04,
      "NRO CUOTA": 0,
      "FECH INIC": "06/02/2010",
      "FECH VENCI": "04/09/2013"
    },
    {
      "CODIGO CLIENTE": 10537305,
      "TIPO DOC": "C",
      "NRO DOC": 10537305,
      "NOMBRE CLIENTE": "GARZON ORTEGA DE NU#EZ JUANA ANGELICA",
      "MONTO PRESTAMO": 2742.88,
      "CODIGO PRESTAMO": 103228150,
      "DIAS MORA": 7861,
      "MONEDA": "MNA",
      "CANT CLIEN": 1,
      "AGENCIA": "HUANDOY",
      "ZONA": "LOS OLIVOS",
      "TERRITORIAL": "MAX MORALES [E]",
      "SUPERVISOR": "ROQUE ORELLANA",
      "EJECUTIVO": "ALCIDES HUACHO",
      "TRAMO": "T F 721-MAS",
      "ESTADO": "C",
      "EDR ANTE": "Harold Chavez",
      "EDR ASIG": "ALCIDES HUACHO",
      "EDR SUPER": "ALCIDES HUACHO",
      "MONTO CUOTA": 0.02,
      "NRO CUOTA": 0,
      "FECH INIC": "07/02/2010",
      "FECH VENCI": "05/09/2013"
    },
    {
      "CODIGO CLIENTE": 8470328,
      "TIPO DOC": "C",
      "NRO DOC": 8470328,
      "NOMBRE CLIENTE": "LOZANO ROCANO SANDRA ANANI",
      "MONTO PRESTAMO": 4090.93,
      "CODIGO PRESTAMO": 112396524,
      "DIAS MORA": 41,
      "MONEDA": "MNA",
      "CANT CLIEN": 85,
      "AGENCIA": "LOS OLIVOS MATRIZ",
      "ZONA": "LOS OLIVOS",
      "TERRITORIAL": "MAX MORALES [E]",
      "SUPERVISOR": "ROQUE ORELLANA",
      "EJECUTIVO": "DENIS ROSALES",
      "TRAMO": "T C 031-060",
      "ESTADO": "A",
      "EDR ANTE": "Harold Chavez",
      "EDR ASIG": "DENIS ROSALES",
      "EDR SUPER": "DENIS ROSALES",
      "MONTO CUOTA": 1082.35,
      "NRO CUOTA": 5,
      "FECH INIC": "08/02/2010",
      "FECH VENCI": "06/09/2013"
    },
    {
      "CODIGO CLIENTE": 6830054,
      "TIPO DOC": "C",
      "NRO DOC": 6830054,
      "NOMBRE CLIENTE": "CABRERA CUEVA JOSE MANUEL",
      "MONTO PRESTAMO": 571.25,
      "CODIGO PRESTAMO": 104980948,
      "DIAS MORA": 1284,
      "MONEDA": "MNA",
      "CANT CLIEN": 90,
      "AGENCIA": "CAJAMARCA MATRIZ",
      "ZONA": "CAJAMARCA",
      "TERRITORIAL": "LUIS CHUQUICHAICO",
      "SUPERVISOR": "JUAN CAMACHO [E]",
      "EJECUTIVO": "ALEX MASGO",
      "TRAMO": "T F 721-MAS",
      "ESTADO": "C",
      "EDR ANTE": "Harold Chavez",
      "EDR ASIG": "ALEX MASGO",
      "EDR SUPER": "ALEX MASGO",
      "MONTO CUOTA": 10.02,
      "NRO CUOTA": 10,
      "FECH INIC": "09/02/2010",
      "FECH VENCI": "07/09/2013"
    },
    {
      "CODIGO CLIENTE": 7365695,
      "TIPO DOC": "C",
      "NRO DOC": 7365695,
      "NOMBRE CLIENTE": "ROJAS COSINGA CARMELA",
      "MONTO PRESTAMO": 1965.06,
      "CODIGO PRESTAMO": 103891979,
      "DIAS MORA": 1494,
      "MONEDA": "MNA",
      "CANT CLIEN": 646,
      "AGENCIA": "LURIN",
      "ZONA": "LURIN",
      "TERRITORIAL": "STEVE CUEVA",
      "SUPERVISOR": "OCTAVIO ALMONTE",
      "EJECUTIVO": "JANNET ROMERO",
      "TRAMO": "T F 721-MAS",
      "ESTADO": "C",
      "EDR ANTE": "Jannet Romero",
      "EDR ASIG": "JANNET ROMERO",
      "EDR SUPER": "JANNET ROMERO",
      "MONTO CUOTA": 120.12,
      "NRO CUOTA": 15,
      "FECH INIC": "10/02/2010",
      "FECH VENCI": "08/09/2013"
    },
    {
      "CODIGO CLIENTE": 9960800,
      "TIPO DOC": "C",
      "NRO DOC": 9960800,
      "NOMBRE CLIENTE": "FERNANDEZ VALVERDE JUAN",
      "MONTO PRESTAMO": 2702.65,
      "CODIGO PRESTAMO": 102504561,
      "DIAS MORA": 2211,
      "MONEDA": "MNA",
      "CANT CLIEN": 1641,
      "AGENCIA": "ANCON",
      "ZONA": "VENTANILLA",
      "TERRITORIAL": "MAX MORALES [E]",
      "SUPERVISOR": "ROQUE ORELLANA",
      "EJECUTIVO": "CESAR TURPO",
      "TRAMO": "T F 721-MAS",
      "ESTADO": "C",
      "EDR ANTE": "Kobranzas",
      "EDR ASIG": "CESAR TURPO",
      "EDR SUPER": "CESAR TURPO",
      "MONTO CUOTA": 209.36,
      "NRO CUOTA": 11,
      "FECH INIC": "11/02/2010",
      "FECH VENCI": "09/09/2013"
    },
    {
      "CODIGO CLIENTE": 10537940,
      "TIPO DOC": "C",
      "NRO DOC": 10537940,
      "NOMBRE CLIENTE": "SOTO GONZALES LUIS ALBERTO",
      "MONTO PRESTAMO": 1517.72,
      "CODIGO PRESTAMO": 100345580,
      "DIAS MORA": 7621,
      "MONEDA": "MNA",
      "CANT CLIEN": 33,
      "AGENCIA": "HUANDOY",
      "ZONA": "LOS OLIVOS",
      "TERRITORIAL": "MAX MORALES [E]",
      "SUPERVISOR": "ROQUE ORELLANA",
      "EJECUTIVO": "FRANKLIN SILVA",
      "TRAMO": "T F 721-MAS",
      "ESTADO": "C",
      "EDR ANTE": "Ronald Tenorio",
      "EDR ASIG": "FRANKLIN SILVA",
      "EDR SUPER": "FRANKLIN SILVA",
      "MONTO CUOTA": 0,
      "NRO CUOTA": 0,
      "FECH INIC": "12/02/2010",
      "FECH VENCI": "10/09/2013"
    },
    {
      "CODIGO CLIENTE": 10364781,
      "TIPO DOC": "C",
      "NRO DOC": 10364781,
      "NOMBRE CLIENTE": "LENES USUCACHI INOCENCIO",
      "MONTO PRESTAMO": 13863.65,
      "CODIGO PRESTAMO": 107258150,
      "DIAS MORA": 569,
      "MONEDA": "MNA",
      "CANT CLIEN": 2,
      "AGENCIA": "GAMARRA",
      "ZONA": "GAMARRA",
      "TERRITORIAL": "LUIS CHUQUICHAICO",
      "SUPERVISOR": "CARLOS CONDORE",
      "EJECUTIVO": "SEVERINO FLORES",
      "TRAMO": "T E 121-720",
      "ESTADO": "C",
      "EDR ANTE": "Ronald Tenorio",
      "EDR ASIG": "SEVERINO FLORES",
      "EDR SUPER": "SEVERINO FLORES",
      "MONTO CUOTA": 1265.29,
      "NRO CUOTA": 16,
      "FECH INIC": "13/02/2010",
      "FECH VENCI": "11/09/2013"
    },
    {
      "CODIGO CLIENTE": 9217325,
      "TIPO DOC": "C",
      "NRO DOC": 9217325,
      "NOMBRE CLIENTE": "CONTRERAS RODRIGUEZ JUANA MARIA",
      "MONTO PRESTAMO": 204,
      "CODIGO PRESTAMO": 100259862,
      "DIAS MORA": 4794,
      "MONEDA": "MNA",
      "CANT CLIEN": 1,
      "AGENCIA": "CANTO GRANDE",
      "ZONA": "S.J. LURIGANCHO",
      "TERRITORIAL": "STEVE CUEVA",
      "SUPERVISOR": "JOSE SILVERIO",
      "EJECUTIVO": "PERCY MAMANI",
      "TRAMO": "T F 721-MAS",
      "ESTADO": "C",
      "EDR ANTE": "Ronald Tenorio",
      "EDR ASIG": "PERCY MAMANI",
      "EDR SUPER": "PERCY MAMANI",
      "MONTO CUOTA": 6.28,
      "NRO CUOTA": 6,
      "FECH INIC": "14/02/2010",
      "FECH VENCI": "12/09/2013"
    },
    {
      "CODIGO CLIENTE": 7182702,
      "TIPO DOC": "C",
      "NRO DOC": 7182702,
      "NOMBRE CLIENTE": "LOPEZ SOLIS CECILIA FILOMENA",
      "MONTO PRESTAMO": 215886.72,
      "CODIGO PRESTAMO": 106630820,
      "DIAS MORA": 891,
      "MONEDA": "MNA",
      "CANT CLIEN": 1,
      "AGENCIA": "LOS OLIVOS MATRIZ",
      "ZONA": "LOS OLIVOS",
      "TERRITORIAL": "MAX MORALES [E]",
      "SUPERVISOR": "MARTIN CUBAS",
      "EJECUTIVO": "JOSE HUAPAYA",
      "TRAMO": "T F 721-MAS",
      "ESTADO": "A",
      "EDR ANTE": "NURY HERRERA",
      "EDR ASIG": "JOSE HUAPAYA",
      "EDR SUPER": "JOSE HUAPAYA",
      "MONTO CUOTA": 6773.28,
      "NRO CUOTA": 10,
      "FECH INIC": "15/02/2010",
      "FECH VENCI": "13/09/2013"
    },
    {
      "CODIGO CLIENTE": 8936772,
      "TIPO DOC": "C",
      "NRO DOC": 8936772,
      "NOMBRE CLIENTE": "CARDICELIS DAZA SERGIO",
      "MONTO PRESTAMO": 782.93,
      "CODIGO PRESTAMO": 111612708,
      "DIAS MORA": 44,
      "MONEDA": "MNA",
      "CANT CLIEN": 7,
      "AGENCIA": "VILLA EL SALVADOR MATRIZ",
      "ZONA": "VILLA EL SALVADOR",
      "TERRITORIAL": "STEVE CUEVA",
      "SUPERVISOR": "FEDOR CARVAJAL",
      "EJECUTIVO": "CESAR TAIPE",
      "TRAMO": "T C 031-060",
      "ESTADO": "A",
      "EDR ANTE": "NURY HERRERA",
      "EDR ASIG": "CESAR TAIPE",
      "EDR SUPER": "CESAR TAIPE",
      "MONTO CUOTA": 128.35,
      "NRO CUOTA": 8,
      "FECH INIC": "16/02/2010",
      "FECH VENCI": "14/09/2013"
    },
    {
      "CODIGO CLIENTE": 10524828,
      "TIPO DOC": "C",
      "NRO DOC": 10524828,
      "NOMBRE CLIENTE": "RODRIGUEZ TANCHIVA CLARA",
      "MONTO PRESTAMO": 3188.97,
      "CODIGO PRESTAMO": 109423703,
      "DIAS MORA": 462,
      "MONEDA": "MNA",
      "CANT CLIEN": 393,
      "AGENCIA": "COCHARCAS",
      "ZONA": "VILLA EL SALVADOR",
      "TERRITORIAL": "STEVE CUEVA",
      "SUPERVISOR": "FEDOR CARVAJAL",
      "EJECUTIVO": "JUAN LEON",
      "TRAMO": "T E 121-720",
      "ESTADO": "C",
      "EDR ANTE": "Yarnold",
      "EDR ASIG": "JUAN LEON",
      "EDR SUPER": "JUAN LEON",
      "MONTO CUOTA": 234.11,
      "NRO CUOTA": 6,
      "FECH INIC": "17/02/2010",
      "FECH VENCI": "15/09/2013"
    },
    {
      "CODIGO CLIENTE": 8952957,
      "TIPO DOC": "C",
      "NRO DOC": 8952957,
      "NOMBRE CLIENTE": "POMA PALACIOS REYNA RUFINA",
      "MONTO PRESTAMO": 3580.05,
      "CODIGO PRESTAMO": 100303523,
      "DIAS MORA": 4612,
      "MONEDA": "MNA",
      "CANT CLIEN": 2,
      "AGENCIA": "JOSE GALVEZ MATRIZ",
      "ZONA": "JOSE GALVEZ",
      "TERRITORIAL": "STEVE CUEVA",
      "SUPERVISOR": "OCTAVIO ALMONTE",
      "EJECUTIVO": "IVAN VASQUEZ",
      "TRAMO": "T F 721-MAS",
      "ESTADO": "C",
      "EDR ANTE": "WILFREDO GOMEZ",
      "EDR ASIG": "IVAN VASQUEZ",
      "EDR SUPER": "IVAN VASQUEZ",
      "MONTO CUOTA": 284.2,
      "NRO CUOTA": 7,
      "FECH INIC": "18/02/2010",
      "FECH VENCI": "16/09/2013"
    },
    {
      "CODIGO CLIENTE": 8952957,
      "TIPO DOC": "C",
      "NRO DOC": 8952957,
      "NOMBRE CLIENTE": "POMA PALACIOS REYNA RUFINA",
      "MONTO PRESTAMO": 2040.1,
      "CODIGO PRESTAMO": 100381130,
      "DIAS MORA": 4590,
      "MONEDA": "MNA",
      "CANT CLIEN": 5,
      "AGENCIA": "JOSE GALVEZ MATRIZ",
      "ZONA": "JOSE GALVEZ",
      "TERRITORIAL": "STEVE CUEVA",
      "SUPERVISOR": "OCTAVIO ALMONTE",
      "EJECUTIVO": "IVAN VASQUEZ",
      "TRAMO": "T F 721-MAS",
      "ESTADO": "C",
      "EDR ANTE": "WILFREDO GOMEZ",
      "EDR ASIG": "IVAN VASQUEZ",
      "EDR SUPER": "IVAN VASQUEZ",
      "MONTO CUOTA": 210.55,
      "NRO CUOTA": 1,
      "FECH INIC": "19/02/2010",
      "FECH VENCI": "17/09/2013"
    }
  ]
}